vsot/__init__.py
vsot/antlr/HTMLLexer.g4
vsot/antlr/HTMLLexer.interp
vsot/antlr/HTMLLexer.py
vsot/antlr/HTMLLexer.tokens
vsot/antlr/HTMLParser.g4
vsot/antlr/HTMLParser.interp
vsot/antlr/HTMLParser.py
vsot/antlr/HTMLParser.tokens
vsot/antlr/HTMLParserVisitor.py
vsot/antlr/__init__.py
vsot/assertions.py
vsot/cli.py
vsot/constants.py
vsot/exceptions.py
vsot/parser.py
vsot/printer.py
vsot/settings.py
vsot/utils.py
vsot-0.1.4.dist-info/entry_points.txt
vsot-0.1.4.dist-info/LICENSE
vsot-0.1.4.dist-info/WHEEL
vsot-0.1.4.dist-info/METADATA
vsot-0.1.4.dist-info/RECORD
