Metadata-Version: 2.1
Name: vsot
Version: 0.1.4
Summary: VSOT - Django/jinja template formatter
Home-page: https://github.com/benhowes/vsot
License: MIT
Keywords: vsot
Author: Ben Howes
Author-email: ben@ben-howes.co.uk
Requires-Python: >=3.6.1
Classifier: Development Status :: 2 - Pre-Alpha
Classifier: Intended Audience :: Developers
Classifier: License :: OSI Approved :: MIT License
Classifier: Natural Language :: English
Classifier: Programming Language :: Python :: 3
Classifier: Programming Language :: Python :: 3.6
Classifier: Programming Language :: Python :: 3.7
Classifier: Programming Language :: Python :: 3.8
Requires-Dist: antlr4-python3-runtime (==4.8)
Requires-Dist: click (>=7.0)
Requires-Dist: dataclasses (>=0.6); python_version < "3.7"
Requires-Dist: pathspec (>=0.8.0,<0.9.0)
